{
    "pk": 136,
    "publish_from": 1770373320.0,
    "publish_to": 1771237320.0,
    "title": "Getting ready for the QGIS User Conference 2026?",
    "image": "https://feed.qgis.org/media/feedimages/2026/02/06/qgis-2026.jpeg",
    "content": "<p>We&rsquo;ve just added conference rates to the recommended accommodation options in Laax!</p>\r\n<p>Joining for the conference, the contributor meeting, or both? You can now start planning your stay using the booking links on the conference website. <strong>Conference rates are valid 2&ndash;11 October 2026.</strong></p>\r\n<p>Looking forward to bringing the QGIS community together in the Swiss Alps - see you in LAAX!</p>\r\n<p><strong>Double-click this entry for more info!</strong></p>",
    "url": "https://feed.qgis.org/136",
    "sticky": false
}